odoo/addons/l10n_be_intrastat_product/README.rst
odoo/addons/l10n_be_intrastat_product/__init__.py
odoo/addons/l10n_be_intrastat_product/__manifest__.py
odoo/addons/l10n_be_intrastat_product/data/intrastat_region.xml
odoo/addons/l10n_be_intrastat_product/doc/intrastat_manual_basis_en.pdf
odoo/addons/l10n_be_intrastat_product/i18n/l10n_be_intrastat_product.pot
odoo/addons/l10n_be_intrastat_product/models/__init__.py
odoo/addons/l10n_be_intrastat_product/models/intrastat_product_declaration.py
odoo/addons/l10n_be_intrastat_product/readme/CONFIGURE.md
odoo/addons/l10n_be_intrastat_product/readme/CONTRIBUTORS.md
odoo/addons/l10n_be_intrastat_product/readme/DESCRIPTION.md
odoo/addons/l10n_be_intrastat_product/readme/HISTORY.md
odoo/addons/l10n_be_intrastat_product/readme/INSTALL.md
odoo/addons/l10n_be_intrastat_product/readme/ROADMAP.md
odoo/addons/l10n_be_intrastat_product/security/intrastat_security.xml
odoo/addons/l10n_be_intrastat_product/static/data/2022_de_intrastat_codes.csv
odoo/addons/l10n_be_intrastat_product/static/data/2022_en_intrastat_codes.csv
odoo/addons/l10n_be_intrastat_product/static/data/2022_fr_intrastat_codes.csv
odoo/addons/l10n_be_intrastat_product/static/data/2022_nl_intrastat_codes.csv
odoo/addons/l10n_be_intrastat_product/static/data/ex19e.xsd
odoo/addons/l10n_be_intrastat_product/static/data/ex19s.xsd
odoo/addons/l10n_be_intrastat_product/static/data/intrastat_x_e.xsd
odoo/addons/l10n_be_intrastat_product/static/data/intrastat_x_s.xsd
odoo/addons/l10n_be_intrastat_product/static/description/icon.png
odoo/addons/l10n_be_intrastat_product/static/description/index.html
odoo/addons/l10n_be_intrastat_product/tests/__init__.py
odoo/addons/l10n_be_intrastat_product/tests/test_intrastat_be.py
odoo/addons/l10n_be_intrastat_product/views/account_move_views.xml
odoo/addons/l10n_be_intrastat_product/views/intrastat_product_views.xml
odoo_addon_l10n_be_intrastat_product-17.0.1.0.0.4.dist-info/METADATA
odoo_addon_l10n_be_intrastat_product-17.0.1.0.0.4.dist-info/WHEEL
odoo_addon_l10n_be_intrastat_product-17.0.1.0.0.4.dist-info/top_level.txt
odoo_addon_l10n_be_intrastat_product-17.0.1.0.0.4.dist-info/RECORD
