Metadata-Version: 2.1
Name: odoo-addon-l10n_be_intrastat_product
Version: 17.0.1.0.0.4
Requires-Python: >=3.10
Requires-Dist: odoo-addon-base_view_inheritance_extension>=17.0dev,<17.1dev
Requires-Dist: odoo-addon-intrastat_product>=17.0dev,<17.1dev
Requires-Dist: odoo>=17.0a,<17.1dev
Summary: Intrastat Product Declaration for Belgium
Home-page: https://github.com/OCA/l10n-belgium
License: AGPL-3
Author: Noviat,Odoo Community Association (OCA)
Author-email: support@odoo-community.org
Classifier: Programming Language :: Python
Classifier: Framework :: Odoo
Classifier: Framework :: Odoo :: 17.0
Classifier: License :: OSI Approved :: GNU Affero General Public License v3
